verkada_py/__init__.py
verkada_py/camera.py
verkada_py/modals.py
verkada_py/organization.py
verkada_py/shared.py
verkada_py-2.0.0.dist-info/LICENSE
verkada_py-2.0.0.dist-info/METADATA
verkada_py-2.0.0.dist-info/WHEEL
verkada_py-2.0.0.dist-info/top_level.txt
verkada_py-2.0.0.dist-info/RECORD
