Metadata-Version: 2.1
Name: verkada-py
Version: 2.0.0
Summary: Unofficial Verkada API Python Library
Home-page: https://github.com/Cyb3r-Jak3/Verkada_py
Author: Cyber_Jake
Author-email: jake@jwhite.network
License: MPL 2.0
Download-URL: https://github.com/Cyb3r-Jak3/Verkada_py/releases/latest
Project-URL: Changelog, https://github.com/Cyb3r-Jak3/Verkada_py/blob/main/CHANGELOG.md
Project-URL: Issues, https://github.com/Cyb3r-Jak3/Verkada_py/issues
Keywords: verkada,restapi
Platform: UNKNOWN
Classifier: Development Status :: 5 - Production/Stable
Classifier: Intended Audience :: Developers
Classifier: License :: OSI Approved :: Mozilla Public License 2.0 (MPL 2.0)
Classifier: Natural Language :: English
Classifier: Programming Language :: Python :: 3 :: Only
Classifier: Programming Language :: Python :: 3
Classifier: Programming Language :: Python :: 3.6
Classifier: Programming Language :: Python :: 3.7
Classifier: Programming Language :: Python :: 3.8
Classifier: Programming Language :: Python :: 3.9
Classifier: Programming Language :: Python :: Implementation :: CPython
Requires-Dist: requests (>=2.25.1)
Requires-Dist: cached-property (>=1.5.2)
